cidade_ibge_tom/__init__py
cidade_ibge_tom/cidade.py
cidade_ibge_tom-0.1.1.dist-info/LICENSE
cidade_ibge_tom-0.1.1.dist-info/WHEEL
cidade_ibge_tom-0.1.1.dist-info/METADATA
cidade_ibge_tom-0.1.1.dist-info/RECORD
