Metadata-Version: 2.1
Name: cidade-ibge-tom
Version: 0.1.1
Summary: Informações da Cidade pelo IBGE ou TOM
License: MIT
Author: Leonardo Gregianin
Author-email: leogregianin@gmail.com
Requires-Python: >=3.7,<4.0
Classifier: License :: OSI Approved :: MIT License
Classifier: Programming Language :: Python :: 3
Classifier: Programming Language :: Python :: 3.7
Classifier: Programming Language :: Python :: 3.8
Requires-Dist: flake8 (>=5.0.4,<6.0.0)
Requires-Dist: mypy (>=0.971,<0.972)
Requires-Dist: pytest (>=7.1.3,<8.0.0)
Requires-Dist: pytest-cov (>=3.0.0,<4.0.0)
